nig.cpython-310-darwin.so
sq_nig-0.1.0.dist-info/RECORD
sq_nig-0.1.0.dist-info/WHEEL
sq_nig-0.1.0.dist-info/top_level.txt
sq_nig-0.1.0.dist-info/METADATA
sq_nig.dylibs/libomp.dylib
